LICENSE
MANIFEST.in
README.md
setup.py
archer_ballistics/__init__.py
py_archer_ballistics.egg-info/PKG-INFO
py_archer_ballistics.egg-info/SOURCES.txt
py_archer_ballistics.egg-info/dependency_links.txt
py_archer_ballistics.egg-info/top_level.txt
py_archer_ballistics.egg-info/zip-safe