Metadata-Version: 2.1
Name: py-archer-ballistics
Version: 1.0.2
Summary: Archer Ballistics Calculator
Home-page: https://github.com/o-murphy/py_archer_ballistics
Author: o-murphy
License: UNKNOWN
Download-URL: http://pypi.python.org/pypi/py_archer_ballistics/
Keywords: async wialon remote api wrapper
Platform: UNKNOWN
Classifier: Development Status :: 5 - Production/Stable
Classifier: Intended Audience :: Developers
Classifier: License :: OSI Approved :: MIT License
Classifier: Natural Language :: English
Classifier: Operating System :: OS Independent
Classifier: Programming Language :: Python
Classifier: Topic :: Software Development :: Libraries :: Python Modules
